pycurrencies/__init__.py
pycurrencies/dolar_scrapper.py
pycurrencies/main.py
pycurrencies-1.0.1.dist-info/METADATA
pycurrencies-1.0.1.dist-info/WHEEL
pycurrencies-1.0.1.dist-info/entry_points.txt
pycurrencies-1.0.1.dist-info/top_level.txt
pycurrencies-1.0.1.dist-info/RECORD
